{
  "US-SLC":{
    "markers":[
      {
        "name":"BV AirNow",
        "sensors":{
          "wind_speed":{
            "sources":[
              {
                "feed":3827,
                "channel":"WS"
              }
            ]
          },
          "wind_direction":{
            "sources":[
              {
                "feed":3827,
                "channel":"WD"
              }
            ]
          },
          "PM25":{
            "sources":[
              {
                "feed":3827,
                "channel":"PM2_5"
              }
            ]
          }
        },
        "latitude":40.897999,
        "longitude":-111.885498,
        "marker_type":"air_now"
      },
      {
        "name":"Rose Park AirNow",
        "sensors":{
          "wind_speed":{
            "sources":[
              {
                "feed":7801,
                "channel":"WS"
              }
            ]
          },
          "wind_direction":{
            "sources":[
              {
                "feed":7801,
                "channel":"WD"
              }
            ]
          },
          "PM25":{
            "sources":[
              {
                "feed":7801,
                "channel":"PM2_5"
              }
            ]
          }
        },
        "latitude":40.7955,
        "longitude":-111.9309,
        "marker_type":"air_now"
      },
      {
        "name":"Hawthorne AirNow",
        "sensors":{
          "wind_speed":{
            "sources":[
              {
                "feed":3833,
                "channel":"WS"
              }
            ]
          },
          "wind_direction":{
            "sources":[
              {
                "feed":3833,
                "channel":"WD"
              }
            ]
          },
          "PM25":{
            "sources":[
              {
                "feed":3833,
                "channel":"PM2_5"
              }
            ]
          }
        },
        "latitude":40.733501,
        "longitude":-111.871696,
        "marker_type":"air_now"
      },
      {
        "name":"Copper View AirNow",
        "sensors":{
          "wind_speed":{
            "sources":[
              {
                "feed":21950,
                "channel":"WS"
              }
            ]
          },
          "wind_direction":{
            "sources":[
              {
                "feed":21950,
                "channel":"WD"
              }
            ]
          },
          "PM25":{
            "sources":[
              {
                "feed":21950,
                "channel":"PM2_5"
              }
            ]
          }
        },
        "latitude":40.598056,
        "longitude":-111.894167,
        "marker_type":"air_now"
      },
      {
        "name":"Herriman #3 AirNow",
        "sensors":{
          "wind_speed":{
            "sources":[
              {
                "feed":12447,
                "channel":"WS"
              }
            ]
          },
          "wind_direction":{
            "sources":[
              {
                "feed":12447,
                "channel":"WD"
              }
            ]
          },
          "PM25":{
            "sources":[
              {
                "feed":12447,
                "channel":"PM2_5"
              }
            ]
          }
        },
        "latitude":40.496408,
        "longitude":-112.036305,
        "marker_type":"air_now"
      },
      {
        "name":"Erda AirNow",
        "sensors":{
          "wind_speed":{
            "sources":[
              {
                "feed":5923,
                "channel":"WS"
              }
            ]
          },
          "wind_direction":{
            "sources":[
              {
                "feed":5923,
                "channel":"WD"
              }
            ]
          },
          "PM25":{
            "sources":[
              {
                "feed":5923,
                "channel":"PM2_5"
              }
            ]
          }
        },
        "latitude":40.600556,
        "longitude":-112.355,
        "marker_type":"air_now"
      },
      {
        "name":"Lindon - Provo AirNow",
        "sensors":{
          "wind_speed":{
            "sources":[
              {
                "feed":3841,
                "channel":"WS"
              }
            ]
          },
          "wind_direction":{
            "sources":[
              {
                "feed":3841,
                "channel":"WD"
              }
            ]
          },
          "PM25":{
            "sources":[
              {
                "feed":3841,
                "channel":"PM2_5"
              }
            ]
          }
        },
        "latitude":40.3414,
        "longitude":-111.7136,
        "marker_type":"air_now"
      },
      {
        "name":"Spanish Fork AirNow",
        "sensors":{
          "wind_speed":{
            "sources":[
              {
                "feed":3842,
                "channel":"WS"
              }
            ]
          },
          "wind_direction":{
            "sources":[
              {
                "feed":3842,
                "channel":"WD"
              }
            ]
          },
          "PM25":{
            "sources":[
              {
                "feed":3842,
                "channel":"PM2_5"
              }
            ]
          }
        },
        "latitude":40.136398,
        "longitude":-111.660202,
        "marker_type":"air_now"
      },
      {
        "name":"Timpanogos Cave AirNow",
        "sensors":{
          "PM25":{
            "sources":[
              {
                "feed":26391,
                "channel":"PM2_5"
              }
            ]
          }
        },
        "latitude":40.44194,
        "longitude":-111.71341,
        "marker_type":"air_now"
      }
    ]
  },
  "US-HOU":{
    "markers":[
      {
        "name":"Seabrook Friendship Park C45 AirNow",
        "sensors":{
          "wind_speed":{
            "sources":[
              {
                "feed":3742,
                "channel":"RWS"
              }
            ]
          },
          "wind_direction":{
            "sources":[
              {
                "feed":3742,
                "channel":"RWD"
              }
            ]
          },
          "PM25":{
            "sources":[
              {
                "feed":3742,
                "channel":"PM2_5"
              }
            ]
          }
        },
        "latitude":29.583100,
        "longitude":-95.015600,
        "marker_type":"air_now"
      },
      {
        "name":"Houston Westhollow C410 AirNow",
        "sensors":{
          "wind_speed":{
            "sources":[
              {
                "feed":3717,
                "channel":"RWS"
              }
            ]
          },
          "wind_direction":{
            "sources":[
              {
                "feed":3717,
                "channel":"RWD"
              }
            ]
          },
          "PM25":{
            "sources":[
              {
                "feed":3717,
                "channel":"PM2_5"
              }
            ]
          }
        },
        "latitude":29.723300,
        "longitude":-95.635800,
        "marker_type":"air_now"
      },
      {
        "name":"Clinton C403 AirNow",
        "sensors":{
          "wind_speed":{
            "sources":[
              {
                "feed":3738,
                "channel":"RWS"
              }
            ]
          },
          "wind_direction":{
            "sources":[
              {
                "feed":3738,
                "channel":"RWD"
              }
            ]
          },
          "PM25":{
            "sources":[
              {
                "feed":3738,
                "channel":"PM2_5"
              }
            ]
          }
        },
        "latitude":29.733900,
        "longitude":-95.257500,
        "marker_type":"air_now"
      },
      {
        "name":"Houston East C1 AirNow",
        "sensors":{
          "wind_speed":{
            "sources":[
              {
                "feed":3737,
                "channel":"RWS"
              }
            ]
          },
          "wind_direction":{
            "sources":[
              {
                "feed":3737,
                "channel":"RWD"
              }
            ]
          },
          "PM25":{
            "sources":[
              {
                "feed":3737,
                "channel":"PM2_5"
              }
            ]
          }
        },
        "latitude":29.768100,
        "longitude":-95.220600,
        "marker_type":"air_now"
      },
      {
        "name":"Baytown C148 AirNow",
        "sensors":{
          "wind_speed":{
            "sources":[
              {
                "feed":3713,
                "channel":"RWS"
              }
            ]
          },
          "wind_direction":{
            "sources":[
              {
                "feed":3713,
                "channel":"RWD"
              }
            ]
          },
          "PM25":{
            "sources":[
              {
                "feed":3713,
                "channel":"PM2_5"
              }
            ]
          }
        },
        "latitude":29.770800,
        "longitude":-95.031100,
        "marker_type":"air_now"
      },
      {
        "name":"Houston North Loop C1052 AirNow",
        "sensors":{
          "wind_speed":{
            "sources":[
              {
                "feed":34239,
                "channel":"RWS"
              }
            ]
          },
          "wind_direction":{
            "sources":[
              {
                "feed":34239,
                "channel":"RWD"
              }
            ]
          },
          "PM25":{
            "sources":[
              {
                "feed":34239,
                "channel":"PM2_5"
              }
            ]
          }
        },
        "latitude":29.814530,
        "longitude":-95.387690,
        "marker_type":"air_now"
      },
      {
        "name":"Houston North Wayside C405 AirNow",
        "sensors":{
          "PM25":{
            "sources":[
              {
                "feed":3708,
                "channel":"PM2_5"
              }
            ]
          }
        },
        "latitude":29.828100,
        "longitude":-95.284200,
        "marker_type":"air_now"
      },
      {
        "name":"Conroe Relocated C78 AirNow",
        "sensors":{
          "wind_speed":{
            "sources":[
              {
                "feed":3771,
                "channel":"RWS"
              }
            ]
          },
          "wind_direction":{
            "sources":[
              {
                "feed":3771,
                "channel":"RWD"
              }
            ]
          },
          "PM25":{
            "sources":[
              {
                "feed":3771,
                "channel":"PM2_5"
              }
            ]
          }
        },
        "latitude":30.350300,
        "longitude":-95.425000,
        "marker_type":"air_now"
      },
      {
        "name":"Hamshire C64 AirNow",
        "sensors":{
          "wind_speed":{
            "sources":[
              {
                "feed":3757,
                "channel":"RWS"
              }
            ]
          },
          "wind_direction":{
            "sources":[
              {
                "feed":3757,
                "channel":"RWD"
              }
            ]
          },
          "PM25":{
            "sources":[
              {
                "feed":3757,
                "channel":"PM2_5"
              }
            ]
          }
        },
        "latitude":29.863952,
        "longitude":-94.317800,
        "marker_type":"air_now"
      }
    ]
  }
}
